[
  {
    "model": "hvz.badgetype",
    "pk": 1,
    "fields": {
      "badge_name": "Tag Streak: Twin-Tag",
      "picture": "badge_icons/streak-02.jpg",
      "badge_type": "g",
      "badge_description": "You tagged two humans within an hour!"
    }
  },
  {
    "model": "hvz.badgetype",
    "pk": 2,
    "fields": {
      "badge_name": "Tag Streak: Triple-Tag",
      "picture": "badge_icons/streak-03.jpg",
      "badge_type": "g",
      "badge_description": "You tagged three humans within an hour!"
    }
  },
  {
    "model": "hvz.badgetype",
    "pk": 3,
    "fields": {
      "badge_name": "Tag Streak: Quad-Tag",
      "picture": "badge_icons/streak-04.jpg",
      "badge_type": "g",
      "badge_description": "You tagged four humans within an hour!"
    }
  },
  {
    "model": "hvz.badgetype",
    "pk": 4,
    "fields": {
      "badge_name": "Tag Streak: Pentag",
      "picture": "badge_icons/streak-05_O4kOYjI.jpg",
      "badge_type": "g",
      "badge_description": "You tagged five humans within an hour!"
    }
  },
  {
    "model": "hvz.badgetype",
    "pk": 5,
    "fields": {
      "badge_name": "Tag Streak: Overkill",
      "picture": "badge_icons/streak-06.jpg",
      "badge_type": "g",
      "badge_description": "You tagged six humans within an hour!"
    }
  },
  {
    "model": "hvz.badgetype",
    "pk": 6,
    "fields": {
      "badge_name": "Tag Streak: Lucky 7",
      "picture": "badge_icons/streak-07.jpg",
      "badge_type": "g",
      "badge_description": "You tagged seven humans within an hour!"
    }
  },
  {
    "model": "hvz.badgetype",
    "pk": 7,
    "fields": {
      "badge_name": "Tag Streak: Tagalicious",
      "picture": "badge_icons/streak-08.jpg",
      "badge_type": "g",
      "badge_description": "You tagged eight humans within an hour!"
    }
  },
  {
    "model": "hvz.badgetype",
    "pk": 8,
    "fields": {
      "badge_name": "Tag Streak: Unstoppable",
      "picture": "badge_icons/streak-09.jpg",
      "badge_type": "g",
      "badge_description": "You tagged nine humans within an hour!"
    }
  },
  {
    "model": "hvz.badgetype",
    "pk": 9,
    "fields": {
      "badge_name": "Tag Streak: Apocalypse",
      "picture": "badge_icons/streak-10.jpg",
      "badge_type": "g",
      "badge_description": "You tagged TEN or more humans within an hour!"
    }
  }
]
